odoo/addons/queue_job_batch/README.rst
odoo/addons/queue_job_batch/__init__.py
odoo/addons/queue_job_batch/__manifest__.py
odoo/addons/queue_job_batch/controllers/__init__.py
odoo/addons/queue_job_batch/controllers/webclient.py
odoo/addons/queue_job_batch/data/queue_job_channel_data.xml
odoo/addons/queue_job_batch/data/queue_job_function_data.xml
odoo/addons/queue_job_batch/i18n/es.po
odoo/addons/queue_job_batch/i18n/fr.po
odoo/addons/queue_job_batch/i18n/it.po
odoo/addons/queue_job_batch/i18n/queue_job_batch.pot
odoo/addons/queue_job_batch/migrations/18.0.1.0.0/pre-migrate.py
odoo/addons/queue_job_batch/models/__init__.py
odoo/addons/queue_job_batch/models/queue_job.py
odoo/addons/queue_job_batch/models/queue_job_batch.py
odoo/addons/queue_job_batch/models/res_users.py
odoo/addons/queue_job_batch/readme/CONTRIBUTORS.md
odoo/addons/queue_job_batch/readme/CREDITS.md
odoo/addons/queue_job_batch/readme/DESCRIPTION.md
odoo/addons/queue_job_batch/readme/USAGE.md
odoo/addons/queue_job_batch/security/ir.model.access.csv
odoo/addons/queue_job_batch/security/security.xml
odoo/addons/queue_job_batch/static/description/icon.png
odoo/addons/queue_job_batch/static/description/icon.svg
odoo/addons/queue_job_batch/static/description/index.html
odoo/addons/queue_job_batch/static/src/MailCoreWeb.esm.js
odoo/addons/queue_job_batch/static/src/QueueJobBatchModel.esm.js
odoo/addons/queue_job_batch/static/src/Store.esm.js
odoo/addons/queue_job_batch/static/src/components/QueueJobBatchMenu.esm.js
odoo/addons/queue_job_batch/static/src/components/QueueJobBatchMenu.scss
odoo/addons/queue_job_batch/static/src/components/QueueJobBatchMenu.xml
odoo/addons/queue_job_batch/views/queue_job_batch_views.xml
odoo/addons/queue_job_batch/views/queue_job_views.xml
odoo_addon_queue_job_batch-18.0.1.0.0.6.dist-info/METADATA
odoo_addon_queue_job_batch-18.0.1.0.0.6.dist-info/WHEEL
odoo_addon_queue_job_batch-18.0.1.0.0.6.dist-info/top_level.txt
odoo_addon_queue_job_batch-18.0.1.0.0.6.dist-info/RECORD
